{
   "created_at":1607443346513,
   "gtin":"08806090306419",
   "offer_fetch_complete":false,
   "offer_urls":{
      "geizhals_DE":"https://geizhals.de/samsung-galaxy-s20-g985f-ds-128gb-cosmic-gray-a2231336.html",
      "google_shopping_SE":"https://www.google.com/shopping/product/2485727905043486611",
      "pricerunner_DK":"/pl/1-5158332/Mobiltelefoner/Samsung-Galaxy-S20-128GB-SM-G985F-DS-Sammenlign-Priser",
      "pricerunner_SE":"/pl/1-5158332/Mobiltelefoner/Samsung-Galaxy-S20-128GB-SM-G985F-DS-priser",
      "pricerunner_UK":"/pl/1-5158332/Mobile-Phones/Samsung-Galaxy-S20-128GB-SM-G985F-DS-Compare-Prices",
      "prisjakt_SE":"5262812"
   },
   "product_token":"gAAAAABfpl8qcdibgIA8Cz5hv41lnaBgkdnOyJnn-BJDXUOStJFMVHb0TF7N2cTjAjkf1LeRqqWxBhn1Xrz5kk5qNZQFYNd2Ug==",
   "triggered_from_client":true,
   "offers":[
      {
         "product_id":null,
         "offer_source":"prisjakt_SE",
         "retail_prod_name":"Samsung G985 S20+ Galaxy 4G 8GB RAM 128GB DS cosmic black",
         "retailer_name":"Mobilyx",
         "country":"SE",
         "price":791900,
         "currency":"SEK",
         "offer_url":"https://www.prisjakt.nu/redirect.php?prisid=3851711771&api_client=1331",
         "requested_at":"2020-12-08 16:02:30.118803",
         "match_score":null,
         "in_stock": "unknown"
      },
      {
         "product_id":null,
         "offer_source":"prisjakt_SE",
         "retail_prod_name":"Samsung Galaxy S20+ - Peksk\u00e4rmsmobil - dual-SIM - 4G LTE - 128 GB - mi",
         "retailer_name":"CDON",
         "country":"SE",
         "price":815900,
         "currency":"SEK",
         "offer_url":"https://www.prisjakt.nu/redirect.php?prisid=3871347893&api_client=1331",
         "requested_at":"2020-12-08 16:02:30.118828",
         "match_score":null,
         "in_stock": "unknown"
      },
      {
         "product_id":null,
         "offer_source":"prisjakt_SE",
         "retail_prod_name":"Samsung Galaxy S20+ 17 cm (6.7) 8 GB 128 GB Dual SIM 4G USB Type-C Gr\u00e5",
         "retailer_name":"ComputerSalg SE",
         "country":"SE",
         "price":815900,
         "currency":"SEK",
         "offer_url":"https://www.prisjakt.nu/redirect.php?prisid=3913341015&api_client=1331",
         "requested_at":"2020-12-08 16:02:30.118834",
         "match_score":null,
         "in_stock": "unknown"
      },
      {
         "product_id":null,
         "offer_source":"prisjakt_SE",
         "retail_prod_name":"Samsung Galaxy S20 Plus 128 GB, 6.7\" QHD+, 64/12/12/10 Mpixel kamera, ",
         "retailer_name":"Databyr\u00e5n",
         "country":"SE",
         "price":839000,
         "currency":"SEK",
         "offer_url":"https://www.prisjakt.nu/redirect.php?prisid=3766433773&api_client=1331",
         "requested_at":"2020-12-08 16:02:30.118839",
         "match_score":null,
         "in_stock": "unknown"
      },
      {
         "product_id":null,
         "offer_source":"prisjakt_SE",
         "retail_prod_name":"Samsung Galaxy S20 Plus 4G 128GB - Cloud Blue",
         "retailer_name":"Proshop",
         "country":"SE",
         "price":879000,
         "currency":"SEK",
         "offer_url":"https://www.prisjakt.nu/redirect.php?prisid=3917529153&api_client=1331",
         "requested_at":"2020-12-08 16:02:30.118844",
         "match_score":null,
         "in_stock": "unknown"
      },
      {
         "product_id":null,
         "offer_source":"prisjakt_SE",
         "retail_prod_name":"Samsung Galaxy S20+ 5G Cloud White #f6f7f4",
         "retailer_name":"Comviq webbutik",
         "country":"SE",
         "price":1199000,
         "currency":"SEK",
         "offer_url":"https://www.prisjakt.nu/redirect.php?prisid=3256502059&api_client=1331",
         "requested_at":"2020-12-08 16:02:30.118852",
         "match_score":null,
         "in_stock": "unknown"
      }
   ],
   "offer_source":"prisjakt",
   "name":null,
   "product_id":null,
   "price":null
}
