{
  "created_at": 1605866599645,
  "gtin": "04960759026477",
  "offer_fetch_complete": false,
  "offer_urls": {
    "geizhals_DE": "https://geizhals.de/nikon-af-s-85mm-1-8g-schwarz-jaa341da-a723246.html",
    "google_shopping_SE": "https://www.google.com/shopping/product/6598605481248207960",
    "pricerunner_DK": "/pl/543-2781875/Kamera-Objektiver/Nikon-AF-S-Nikkor-85mm-F1.8G-Sammenlign-Priser",
    "pricerunner_SE": "/pl/543-2781875/Kameraobjektiv/Nikon-AF-S-Nikkor-85mm-F1.8G-priser",
    "pricerunner_UK": "/pl/543-2781875/Camera-Lenses/Nikon-AF-S-Nikkor-85mm-F1.8G-Compare-Prices",
    "prisjakt_SE": "1085167"
  },
  "product_token": "gAAAAABfmH8E_RByzwQBUz9csR4Hgu0GrTy3zOtLP2SqWZsu6pyg-bpkENsvI6pWr7BGvx-cpGtbSem1vO_wNoU3FUOO1llhhg==",
  "triggered_from_client": true,
  "offers": [
    {
      "product_id": null,
      "offer_source": "kelkoo_NO",
      "retail_prod_name": "Nikon 85mm F/1,8g Af-S Nikkor",
      "retailer_name": "Foto.no",
      "country": "NO",
      "price": "559900",
      "currency": "NOK",
      "offer_url": "https://no-go.kelkoogroup.net/ctl/go/sitesearchGo?.ts=1605866603018&.sig=fF1F_v5wGMQ3cNNnJ6jbUd0AtFc-&affiliationId=96954748&catId=124701&comId=16109413&contextLevel=1&contextOfferPosition=1&contextPageSize=1&country=no&ecs=ok&merchantid=16109413&offerId=46b55d9a833ba2eb94634788471fdd88&searchId=10769920429900_1605866603009_21144&searchQuery=&service=5&wait=true",
      "requested_at": "2020-11-20 10:03:23.028599",
      "match_score": 1
    },
    {
      "product_id": null,
      "offer_source": "kelkoo_SE",
      "retail_prod_name": "Nikon AF-S 85/1,8G",
      "retailer_name": "CyberPhoto",
      "country": "SE",
      "price": "519000",
      "currency": "SEK",
      "offer_url": "https://se-go.kelkoogroup.net/ctl/go/sitesearchGo?.ts=1605866603081&.sig=Z91Y1el2IJO6lF_nB2UcIqYz9vM-&affiliationId=96954747&catId=124701&comId=3375501&contextLevel=1&contextOfferPosition=1&contextPageSize=2&country=se&ecs=ok&merchantid=3375501&offerId=738332405b6535bccacaf099a6ed99de&searchId=10769825018469_1605866603074_42889&searchQuery=&service=5&wait=true",
      "requested_at": "2020-11-20 10:03:23.092546",
      "match_score": 1
    },
    {
      "product_id": null,
      "offer_source": "kelkoo_SE",
      "retail_prod_name": "Nikon AF-S Nikkor 85mm f/1,8G",
      "retailer_name": "Scandinavianphoto.se",
      "country": "SE",
      "price": "499000",
      "currency": "SEK",
      "offer_url": "https://se-go.kelkoogroup.net/ctl/go/sitesearchGo?.ts=1605866603082&.sig=1fxWUfQ2XDcUJmYDmqxMX1OTT7k-&affiliationId=96954747&catId=124701&comId=10189823&contextLevel=1&contextOfferPosition=2&contextPageSize=2&country=se&ecs=ok&merchantid=10189823&offerId=df8f37e9da206e5e570cd58be8a2d128&searchId=10769825018469_1605866603074_42889&searchQuery=&service=5&wait=true",
      "requested_at": "2020-11-20 10:03:23.092571",
      "match_score": 1
    }
  ],
  "offer_source": "kelkoo",
  "name": null,
  "product_id": null,
  "price": null
}
